nifty_anilist/__init__.py
nifty_anilist/anilist_client.py
nifty_anilist/auth.py
nifty_anilist/logging.py
nifty_anilist/settings.py
nifty_anilist/client/__init__.py
nifty_anilist/client/async_base_client.py
nifty_anilist/client/base_model.py
nifty_anilist/client/base_operation.py
nifty_anilist/client/client.py
nifty_anilist/client/custom_fields.py
nifty_anilist/client/custom_mutations.py
nifty_anilist/client/custom_queries.py
nifty_anilist/client/custom_typing_fields.py
nifty_anilist/client/enums.py
nifty_anilist/client/exceptions.py
nifty_anilist/client/input_types.py
nifty_anilist/prebuilt/__init__.py
nifty_anilist/prebuilt/common.py
nifty_anilist/prebuilt/media.py
nifty_anilist/prebuilt/media_list.py
nifty_anilist/utils/__init__.py
nifty_anilist/utils/auth_utils.py
nifty_anilist/utils/model_utils.py
nifty_anilist/utils/request_utils.py
nifty_anilist-0.1.7.dist-info/licenses/LICENSE
nifty_anilist-0.1.7.dist-info/METADATA
nifty_anilist-0.1.7.dist-info/WHEEL
nifty_anilist-0.1.7.dist-info/top_level.txt
nifty_anilist-0.1.7.dist-info/RECORD
