Metadata-Version: 2.4
Name: nifty_anilist
Version: 0.1.7
Summary: Utilities for the Anilist GraphQL API.
Author-email: Alexey Polishchuk <alexpolishchukmail@gmail.com>
License-Expression: MIT
Project-URL: Repository, https://github.com/AlexPolGit/nifty-anilist
Requires-Python: >=3.12
License-File: LICENSE
Requires-Dist: asyncio>=4.0.0
Requires-Dist: colorama>=0.4.6
Requires-Dist: graphql-core>=3.2.6
Requires-Dist: httpx>=0.28.1
Requires-Dist: keyring>=25.6.0
Requires-Dist: pydantic>=2.11.9
Requires-Dist: pydantic-settings>=2.11.0
Requires-Dist: pyjwt>=2.10.1
Requires-Dist: python-dotenv>=1.1.1
Requires-Dist: selenium>=4.35.0
Requires-Dist: structlog>=25.4.0
Dynamic: license-file
